moore_math_beta/__init__.py
moore_math_beta-0.3.1.dist-info/METADATA
moore_math_beta-0.3.1.dist-info/WHEEL
moore_math_beta-0.3.1.dist-info/top_level.txt
moore_math_beta-0.3.1.dist-info/RECORD
