Metadata-Version: 2.1
Name: moore-math-beta
Version: 0.3.1
Summary: quick maths
Home-page: UNKNOWN
Author: abhinav suri
Author-email: suria@sas.upenn.edu
License: MIT
Platform: UNKNOWN
